CLTFaceDetectUtils/__init__.py
CLTFaceDetectUtils/faceDetection.py
CLTFaceDetectUtils-1.0.0.dist-info/METADATA
CLTFaceDetectUtils-1.0.0.dist-info/WHEEL
CLTFaceDetectUtils-1.0.0.dist-info/top_level.txt
CLTFaceDetectUtils-1.0.0.dist-info/RECORD
