Metadata-Version: 2.1
Name: CLTFaceDetectUtils
Version: 1.0.0
Summary: utility functions to detect faces using haar cascades
Home-page: UNKNOWN
Author: melkorCba
Author-email: dadcbds@gmail.com
License: MIT
Platform: UNKNOWN
